{
  "strategy": "DiverT Strategy",
  "updatedAt": "2026-05-05T06:00:38.304743+00:00",
  "lastScan": {
    "status": "success",
    "newSignals": 1,
    "nextScanAt": "2026-05-05T06:30:38.304743+00:00"
  },
  "rows": [
    {
      "symbol": "BTCUSDT",
      "signal": "NO",
      "side": "NONE",
      "quality": "FRAGILE",
      "invalidation": null,
      "scanPrice": 80946.0,
      "sourceVenue": "hyper",
      "notes": [
        "Nu exista inca o structura DiverT valida pe buy sau sell",
        "price_now=80946.0"
      ],
      "patternContext": "neutral",
      "entryStructure": "no_valid_divert_v0_3_signal",
      "risk": "high",
      "timeframe": "4h",
      "execution": {
        "status": "none",
        "entry": "no action",
        "invalidation": null,
        "exitTrigger": "none",
        "closeRule": "none"
      },
      "setupKey": null,
      "setupIndex": null,
      "setupTimestamp": null,
      "setupState": "idle"
    },
    {
      "symbol": "ETHUSDT",
      "signal": "NO",
      "side": "NONE",
      "quality": "FRAGILE",
      "invalidation": null,
      "scanPrice": 2379.7,
      "sourceVenue": "hyper",
      "notes": [
        "Nu exista inca o structura DiverT valida pe buy sau sell",
        "price_now=2379.7"
      ],
      "patternContext": "neutral",
      "entryStructure": "no_valid_divert_v0_3_signal",
      "risk": "high",
      "timeframe": "4h",
      "execution": {
        "status": "none",
        "entry": "no action",
        "invalidation": null,
        "exitTrigger": "none",
        "closeRule": "none"
      },
      "setupKey": null,
      "setupIndex": null,
      "setupTimestamp": null,
      "setupState": "idle"
    },
    {
      "symbol": "SOLUSDT",
      "signal": "NO",
      "side": "NONE",
      "quality": "FRAGILE",
      "invalidation": null,
      "scanPrice": 84.898,
      "sourceVenue": "hyper",
      "notes": [
        "Nu exista inca o structura DiverT valida pe buy sau sell",
        "price_now=84.898"
      ],
      "patternContext": "neutral",
      "entryStructure": "no_valid_divert_v0_3_signal",
      "risk": "high",
      "timeframe": "4h",
      "execution": {
        "status": "none",
        "entry": "no action",
        "invalidation": null,
        "exitTrigger": "none",
        "closeRule": "none"
      },
      "setupKey": null,
      "setupIndex": null,
      "setupTimestamp": null,
      "setupState": "idle"
    },
    {
      "symbol": "XRPUSDT",
      "signal": "NO",
      "side": "NONE",
      "quality": "FRAGILE",
      "invalidation": null,
      "scanPrice": 1.4018,
      "sourceVenue": "hyper",
      "notes": [
        "Nu exista inca o structura DiverT valida pe buy sau sell",
        "price_now=1.4018"
      ],
      "patternContext": "neutral",
      "entryStructure": "no_valid_divert_v0_3_signal",
      "risk": "high",
      "timeframe": "4h",
      "execution": {
        "status": "none",
        "entry": "no action",
        "invalidation": null,
        "exitTrigger": "none",
        "closeRule": "none"
      },
      "setupKey": null,
      "setupIndex": null,
      "setupTimestamp": null,
      "setupState": "idle"
    },
    {
      "symbol": "AAVEUSDT",
      "signal": "NO",
      "side": "NONE",
      "quality": "FRAGILE",
      "invalidation": null,
      "scanPrice": 92.996,
      "sourceVenue": "hyper",
      "notes": [
        "Nu exista inca o structura DiverT valida pe buy sau sell",
        "price_now=92.996"
      ],
      "patternContext": "neutral",
      "entryStructure": "no_valid_divert_v0_3_signal",
      "risk": "high",
      "timeframe": "4h",
      "execution": {
        "status": "none",
        "entry": "no action",
        "invalidation": null,
        "exitTrigger": "none",
        "closeRule": "none"
      },
      "setupKey": null,
      "setupIndex": null,
      "setupTimestamp": null,
      "setupState": "idle"
    },
    {
      "symbol": "XMRUSDT",
      "signal": "NO",
      "side": "NONE",
      "quality": "FRAGILE",
      "invalidation": null,
      "scanPrice": 409.46,
      "sourceVenue": "hyper",
      "notes": [
        "Nu exista inca o structura DiverT valida pe buy sau sell",
        "price_now=409.46"
      ],
      "patternContext": "neutral",
      "entryStructure": "no_valid_divert_v0_3_signal",
      "risk": "high",
      "timeframe": "4h",
      "execution": {
        "status": "none",
        "entry": "no action",
        "invalidation": null,
        "exitTrigger": "none",
        "closeRule": "none"
      },
      "setupKey": null,
      "setupIndex": null,
      "setupTimestamp": null,
      "setupState": "idle"
    },
    {
      "symbol": "DOGEUSDT",
      "signal": "NEAR_SETUP",
      "side": "SELL",
      "quality": "WATCH",
      "invalidation": 0.11383,
      "scanPrice": 0.11177,
      "sourceVenue": "hyper",
      "notes": [
        "Sell setup almost valid",
        "RSI LH exista, dar high-ul valid nu este inca in banda 68-72",
        "Aproape de confirmare",
        "price_now=0.11177"
      ],
      "patternContext": "neutral",
      "entryStructure": "sell_divert_near_setup_v0_3",
      "risk": "medium_high",
      "timeframe": "4h",
      "execution": {
        "status": "near",
        "entry": "wait for RSI threshold confirmation",
        "invalidation": 0.11383,
        "exitTrigger": "no entry yet",
        "closeRule": "none"
      },
      "setupKey": "sell:264:292:264:292",
      "setupIndex": 292,
      "setupTimestamp": "2026-05-04T00:00:00+00:00",
      "setupState": "near"
    },
    {
      "symbol": "BNBUSDT",
      "signal": "NO",
      "side": "NONE",
      "quality": "FRAGILE",
      "invalidation": null,
      "scanPrice": 627.95,
      "sourceVenue": "hyper",
      "notes": [
        "Nu exista inca o structura DiverT valida pe buy sau sell",
        "price_now=627.95"
      ],
      "patternContext": "neutral",
      "entryStructure": "no_valid_divert_v0_3_signal",
      "risk": "high",
      "timeframe": "4h",
      "execution": {
        "status": "none",
        "entry": "no action",
        "invalidation": null,
        "exitTrigger": "none",
        "closeRule": "none"
      },
      "setupKey": null,
      "setupIndex": null,
      "setupTimestamp": null,
      "setupState": "idle"
    },
    {
      "symbol": "TAOUSDT",
      "signal": "NO",
      "side": "NONE",
      "quality": "FRAGILE",
      "invalidation": null,
      "scanPrice": 285.42,
      "sourceVenue": "hyper",
      "notes": [
        "Nu exista inca o structura DiverT valida pe buy sau sell",
        "price_now=285.42"
      ],
      "patternContext": "neutral",
      "entryStructure": "no_valid_divert_v0_3_signal",
      "risk": "high",
      "timeframe": "4h",
      "execution": {
        "status": "none",
        "entry": "no action",
        "invalidation": null,
        "exitTrigger": "none",
        "closeRule": "none"
      },
      "setupKey": null,
      "setupIndex": null,
      "setupTimestamp": null,
      "setupState": "idle"
    },
    {
      "symbol": "SUIUSDT",
      "signal": "NO",
      "side": "NONE",
      "quality": "FRAGILE",
      "invalidation": null,
      "scanPrice": 0.94475,
      "sourceVenue": "hyper",
      "notes": [
        "Nu exista inca o structura DiverT valida pe buy sau sell",
        "price_now=0.94475"
      ],
      "patternContext": "neutral",
      "entryStructure": "no_valid_divert_v0_3_signal",
      "risk": "high",
      "timeframe": "4h",
      "execution": {
        "status": "none",
        "entry": "no action",
        "invalidation": null,
        "exitTrigger": "none",
        "closeRule": "none"
      },
      "setupKey": null,
      "setupIndex": null,
      "setupTimestamp": null,
      "setupState": "idle"
    },
    {
      "symbol": "ARBUSDT",
      "signal": "NO",
      "side": "NONE",
      "quality": "FRAGILE",
      "invalidation": null,
      "scanPrice": 0.1172,
      "sourceVenue": "hyper",
      "notes": [
        "Nu exista inca o structura DiverT valida pe buy sau sell",
        "price_now=0.1172"
      ],
      "patternContext": "negative",
      "entryStructure": "no_valid_divert_v0_3_signal",
      "risk": "high",
      "timeframe": "4h",
      "execution": {
        "status": "none",
        "entry": "no action",
        "invalidation": null,
        "exitTrigger": "none",
        "closeRule": "none"
      },
      "setupKey": null,
      "setupIndex": null,
      "setupTimestamp": null,
      "setupState": "idle"
    },
    {
      "symbol": "ZROUSDT",
      "signal": "NO",
      "side": "NONE",
      "quality": "EXPIRED",
      "invalidation": null,
      "scanPrice": 1.4685,
      "sourceVenue": "hyper",
      "notes": [
        "Buy setup expirat",
        "Setup mai vechi de 30 lumanari 4H",
        "price_now=1.4685"
      ],
      "patternContext": "neutral",
      "entryStructure": "expired_buy_divert_v0_3",
      "risk": "high",
      "timeframe": "4h",
      "execution": {
        "status": "none",
        "entry": "no action",
        "invalidation": null,
        "exitTrigger": "none",
        "closeRule": "none"
      },
      "setupKey": "buy:258:266:254:266",
      "setupIndex": 266,
      "setupTimestamp": "2026-04-29T16:00:00+00:00",
      "setupState": "expired"
    },
    {
      "symbol": "AVAXUSDT",
      "signal": "NO",
      "side": "NONE",
      "quality": "FRAGILE",
      "invalidation": null,
      "scanPrice": 9.302,
      "sourceVenue": "hyper",
      "notes": [
        "Nu exista inca o structura DiverT valida pe buy sau sell",
        "price_now=9.302"
      ],
      "patternContext": "neutral",
      "entryStructure": "no_valid_divert_v0_3_signal",
      "risk": "high",
      "timeframe": "4h",
      "execution": {
        "status": "none",
        "entry": "no action",
        "invalidation": null,
        "exitTrigger": "none",
        "closeRule": "none"
      },
      "setupKey": null,
      "setupIndex": null,
      "setupTimestamp": null,
      "setupState": "idle"
    },
    {
      "symbol": "LINKUSDT",
      "signal": "NO",
      "side": "NONE",
      "quality": "FRAGILE",
      "invalidation": null,
      "scanPrice": 9.5569,
      "sourceVenue": "hyper",
      "notes": [
        "Nu exista inca o structura DiverT valida pe buy sau sell",
        "price_now=9.5569"
      ],
      "patternContext": "neutral",
      "entryStructure": "no_valid_divert_v0_3_signal",
      "risk": "high",
      "timeframe": "4h",
      "execution": {
        "status": "none",
        "entry": "no action",
        "invalidation": null,
        "exitTrigger": "none",
        "closeRule": "none"
      },
      "setupKey": null,
      "setupIndex": null,
      "setupTimestamp": null,
      "setupState": "idle"
    },
    {
      "symbol": "ADAUSDT",
      "signal": "NO",
      "side": "NONE",
      "quality": "FRAGILE",
      "invalidation": null,
      "scanPrice": 0.25299,
      "sourceVenue": "hyper",
      "notes": [
        "Nu exista inca o structura DiverT valida pe buy sau sell",
        "price_now=0.25299"
      ],
      "patternContext": "neutral",
      "entryStructure": "no_valid_divert_v0_3_signal",
      "risk": "high",
      "timeframe": "4h",
      "execution": {
        "status": "none",
        "entry": "no action",
        "invalidation": null,
        "exitTrigger": "none",
        "closeRule": "none"
      },
      "setupKey": null,
      "setupIndex": null,
      "setupTimestamp": null,
      "setupState": "idle"
    },
    {
      "symbol": "NEARUSDT",
      "signal": "NO",
      "side": "NONE",
      "quality": "FRAGILE",
      "invalidation": null,
      "scanPrice": 1.2772,
      "sourceVenue": "hyper",
      "notes": [
        "Nu exista inca o structura DiverT valida pe buy sau sell",
        "price_now=1.2772"
      ],
      "patternContext": "neutral",
      "entryStructure": "no_valid_divert_v0_3_signal",
      "risk": "high",
      "timeframe": "4h",
      "execution": {
        "status": "none",
        "entry": "no action",
        "invalidation": null,
        "exitTrigger": "none",
        "closeRule": "none"
      },
      "setupKey": null,
      "setupIndex": null,
      "setupTimestamp": null,
      "setupState": "idle"
    },
    {
      "symbol": "BCHUSDT",
      "signal": "NO",
      "side": "NONE",
      "quality": "FRAGILE",
      "invalidation": null,
      "scanPrice": 445.22,
      "sourceVenue": "hyper",
      "notes": [
        "Nu exista inca o structura DiverT valida pe buy sau sell",
        "price_now=445.22"
      ],
      "patternContext": "neutral",
      "entryStructure": "no_valid_divert_v0_3_signal",
      "risk": "high",
      "timeframe": "4h",
      "execution": {
        "status": "none",
        "entry": "no action",
        "invalidation": null,
        "exitTrigger": "none",
        "closeRule": "none"
      },
      "setupKey": null,
      "setupIndex": null,
      "setupTimestamp": null,
      "setupState": "idle"
    },
    {
      "symbol": "TONUSDT",
      "signal": "NO",
      "side": "NONE",
      "quality": "FRAGILE",
      "invalidation": null,
      "scanPrice": 1.7442,
      "sourceVenue": "hyper",
      "notes": [
        "Nu exista inca o structura DiverT valida pe buy sau sell",
        "price_now=1.7442"
      ],
      "patternContext": "positive",
      "entryStructure": "no_valid_divert_v0_3_signal",
      "risk": "high",
      "timeframe": "4h",
      "execution": {
        "status": "none",
        "entry": "no action",
        "invalidation": null,
        "exitTrigger": "none",
        "closeRule": "none"
      },
      "setupKey": null,
      "setupIndex": null,
      "setupTimestamp": null,
      "setupState": "idle"
    },
    {
      "symbol": "TRXUSDT",
      "signal": "NO",
      "side": "NONE",
      "quality": "FRAGILE",
      "invalidation": null,
      "scanPrice": 0.33899,
      "sourceVenue": "hyper",
      "notes": [
        "Nu exista inca o structura DiverT valida pe buy sau sell",
        "price_now=0.33899"
      ],
      "patternContext": "neutral",
      "entryStructure": "no_valid_divert_v0_3_signal",
      "risk": "high",
      "timeframe": "4h",
      "execution": {
        "status": "none",
        "entry": "no action",
        "invalidation": null,
        "exitTrigger": "none",
        "closeRule": "none"
      },
      "setupKey": null,
      "setupIndex": null,
      "setupTimestamp": null,
      "setupState": "idle"
    },
    {
      "symbol": "UNIUSDT",
      "signal": "NO",
      "side": "NONE",
      "quality": "FRAGILE",
      "invalidation": null,
      "scanPrice": 3.3339,
      "sourceVenue": "hyper",
      "notes": [
        "Nu exista inca o structura DiverT valida pe buy sau sell",
        "price_now=3.3339"
      ],
      "patternContext": "neutral",
      "entryStructure": "no_valid_divert_v0_3_signal",
      "risk": "high",
      "timeframe": "4h",
      "execution": {
        "status": "none",
        "entry": "no action",
        "invalidation": null,
        "exitTrigger": "none",
        "closeRule": "none"
      },
      "setupKey": null,
      "setupIndex": null,
      "setupTimestamp": null,
      "setupState": "idle"
    },
    {
      "symbol": "CRVUSDT",
      "signal": "NO",
      "side": "NONE",
      "quality": "FRAGILE",
      "invalidation": null,
      "scanPrice": 0.23957,
      "sourceVenue": "hyper",
      "notes": [
        "Nu exista inca o structura DiverT valida pe buy sau sell",
        "price_now=0.23957"
      ],
      "patternContext": "neutral",
      "entryStructure": "no_valid_divert_v0_3_signal",
      "risk": "high",
      "timeframe": "4h",
      "execution": {
        "status": "none",
        "entry": "no action",
        "invalidation": null,
        "exitTrigger": "none",
        "closeRule": "none"
      },
      "setupKey": null,
      "setupIndex": null,
      "setupTimestamp": null,
      "setupState": "idle"
    },
    {
      "symbol": "WLDUSDT",
      "signal": "NO",
      "side": "NONE",
      "quality": "FRAGILE",
      "invalidation": null,
      "scanPrice": 0.24405,
      "sourceVenue": "hyper",
      "notes": [
        "Nu exista inca o structura DiverT valida pe buy sau sell",
        "price_now=0.24405"
      ],
      "patternContext": "neutral",
      "entryStructure": "no_valid_divert_v0_3_signal",
      "risk": "high",
      "timeframe": "4h",
      "execution": {
        "status": "none",
        "entry": "no action",
        "invalidation": null,
        "exitTrigger": "none",
        "closeRule": "none"
      },
      "setupKey": null,
      "setupIndex": null,
      "setupTimestamp": null,
      "setupState": "idle"
    },
    {
      "symbol": "LTCUSDT",
      "signal": "NO",
      "side": "NONE",
      "quality": "FRAGILE",
      "invalidation": null,
      "scanPrice": 55.2,
      "sourceVenue": "hyper",
      "notes": [
        "Nu exista inca o structura DiverT valida pe buy sau sell",
        "price_now=55.2"
      ],
      "patternContext": "neutral",
      "entryStructure": "no_valid_divert_v0_3_signal",
      "risk": "high",
      "timeframe": "4h",
      "execution": {
        "status": "none",
        "entry": "no action",
        "invalidation": null,
        "exitTrigger": "none",
        "closeRule": "none"
      },
      "setupKey": null,
      "setupIndex": null,
      "setupTimestamp": null,
      "setupState": "idle"
    },
    {
      "symbol": "JUPUSDT",
      "signal": "NO",
      "side": "NONE",
      "quality": "FRAGILE",
      "invalidation": null,
      "scanPrice": 0.18523,
      "sourceVenue": "hyper",
      "notes": [
        "Nu exista inca o structura DiverT valida pe buy sau sell",
        "price_now=0.18523"
      ],
      "patternContext": "neutral",
      "entryStructure": "no_valid_divert_v0_3_signal",
      "risk": "high",
      "timeframe": "4h",
      "execution": {
        "status": "none",
        "entry": "no action",
        "invalidation": null,
        "exitTrigger": "none",
        "closeRule": "none"
      },
      "setupKey": null,
      "setupIndex": null,
      "setupTimestamp": null,
      "setupState": "idle"
    },
    {
      "symbol": "WIFUSDT",
      "signal": "NO",
      "side": "NONE",
      "quality": "FRAGILE",
      "invalidation": null,
      "scanPrice": 0.19284,
      "sourceVenue": "hyper",
      "notes": [
        "Nu exista inca o structura DiverT valida pe buy sau sell",
        "price_now=0.19284"
      ],
      "patternContext": "neutral",
      "entryStructure": "no_valid_divert_v0_3_signal",
      "risk": "high",
      "timeframe": "4h",
      "execution": {
        "status": "none",
        "entry": "no action",
        "invalidation": null,
        "exitTrigger": "none",
        "closeRule": "none"
      },
      "setupKey": null,
      "setupIndex": null,
      "setupTimestamp": null,
      "setupState": "idle"
    },
    {
      "symbol": "RUNEUSDT",
      "signal": "WATCH",
      "side": "SELL",
      "quality": "MEDIUM",
      "invalidation": 0.538,
      "scanPrice": 0.53208,
      "sourceVenue": "hyper",
      "notes": [
        "Sell DiverT setup valid",
        "Prima structura valida in banda 68-72 confirmata",
        "Invalidarea defensiva este high-ul setupului",
        "price_now=0.53208",
        "same_side_blocked_48h"
      ],
      "patternContext": "neutral",
      "entryStructure": "sell_divert_v0_3",
      "risk": "medium_high",
      "timeframe": "4h",
      "execution": {
        "status": "cooldown_active",
        "entry": "same-side setup blocked during 48h cooldown",
        "invalidation": 0.538,
        "exitTrigger": "wait for cooldown expiry or new structure",
        "closeRule": "none"
      },
      "setupKey": "sell:250:293:250:292",
      "setupIndex": 293,
      "setupTimestamp": "2026-05-04T04:00:00+00:00",
      "setupState": "cooldown"
    },
    {
      "symbol": "AEROUSDT",
      "signal": "ERROR",
      "side": "NONE",
      "quality": "UNKNOWN",
      "invalidation": null,
      "scanPrice": 0.45254,
      "sourceVenue": "hyper",
      "notes": [
        "Eroare la generare: HTTP Error 400: Bad Request",
        "price_now=0.45254"
      ],
      "patternContext": "unknown",
      "entryStructure": "error",
      "risk": "unknown",
      "timeframe": "4h",
      "execution": {
        "status": "none",
        "entry": "no action",
        "invalidation": null,
        "exitTrigger": "none",
        "closeRule": "none"
      },
      "setupKey": null,
      "setupIndex": null,
      "setupTimestamp": null,
      "setupState": "idle"
    },
    {
      "symbol": "APTUSDT",
      "signal": "NO",
      "side": "NONE",
      "quality": "FRAGILE",
      "invalidation": null,
      "scanPrice": 0.9746,
      "sourceVenue": "hyper",
      "notes": [
        "Nu exista inca o structura DiverT valida pe buy sau sell",
        "price_now=0.9746"
      ],
      "patternContext": "neutral",
      "entryStructure": "no_valid_divert_v0_3_signal",
      "risk": "high",
      "timeframe": "4h",
      "execution": {
        "status": "none",
        "entry": "no action",
        "invalidation": null,
        "exitTrigger": "none",
        "closeRule": "none"
      },
      "setupKey": null,
      "setupIndex": null,
      "setupTimestamp": null,
      "setupState": "idle"
    },
    {
      "symbol": "DOTUSDT",
      "signal": "NO",
      "side": "NONE",
      "quality": "FRAGILE",
      "invalidation": null,
      "scanPrice": 1.2461,
      "sourceVenue": "hyper",
      "notes": [
        "Nu exista inca o structura DiverT valida pe buy sau sell",
        "price_now=1.2461"
      ],
      "patternContext": "neutral",
      "entryStructure": "no_valid_divert_v0_3_signal",
      "risk": "high",
      "timeframe": "4h",
      "execution": {
        "status": "none",
        "entry": "no action",
        "invalidation": null,
        "exitTrigger": "none",
        "closeRule": "none"
      },
      "setupKey": null,
      "setupIndex": null,
      "setupTimestamp": null,
      "setupState": "idle"
    },
    {
      "symbol": "HBARUSDT",
      "signal": "NO",
      "side": "NONE",
      "quality": "FRAGILE",
      "invalidation": null,
      "scanPrice": 0.088484,
      "sourceVenue": "hyper",
      "notes": [
        "Nu exista inca o structura DiverT valida pe buy sau sell",
        "price_now=0.088484"
      ],
      "patternContext": "neutral",
      "entryStructure": "no_valid_divert_v0_3_signal",
      "risk": "high",
      "timeframe": "4h",
      "execution": {
        "status": "none",
        "entry": "no action",
        "invalidation": null,
        "exitTrigger": "none",
        "closeRule": "none"
      },
      "setupKey": null,
      "setupIndex": null,
      "setupTimestamp": null,
      "setupState": "idle"
    }
  ]
}