[
  {
    "symbol": "BTCUSDT",
    "side": "BUY",
    "timeframe": "4h",
    "status": "open",
    "entryPrice": 78214.0,
    "invalidationPrice": 65000.0,
    "exitPrice": null,
    "resultPct": -0.05,
    "quality": "GOOD",
    "openedAt": "2026-04-22T11:07:49.334891+00:00",
    "closedAt": null,
    "targetPrice": 80560.42,
    "exitRule": "close on target or invalidation",
    "notes": [
      "auto_managed",
      "alert:entry_ready",
      "live:price=78175.0",
      "live:pnlPct=-0.05",
      "live:distanceToInvalidationPct=16.85"
    ]
  },
  {
    "symbol": "ETHUSDT",
    "side": "BUY",
    "timeframe": "4h",
    "status": "open",
    "entryPrice": 2389.9,
    "invalidationPrice": 1938.82,
    "exitPrice": null,
    "resultPct": 0.02,
    "quality": "GOOD",
    "openedAt": "2026-04-22T11:07:49.334891+00:00",
    "closedAt": null,
    "targetPrice": 2461.597,
    "exitRule": "close on target or invalidation",
    "notes": [
      "auto_managed",
      "alert:entry_ready",
      "live:price=2390.3",
      "live:pnlPct=0.02",
      "live:distanceToInvalidationPct=18.89"
    ]
  },
  {
    "symbol": "SOLUSDT",
    "side": "BUY",
    "timeframe": "4h",
    "status": "open",
    "entryPrice": 88.294,
    "invalidationPrice": 78.96,
    "exitPrice": null,
    "resultPct": -0.1,
    "quality": "MEDIUM",
    "openedAt": "2026-04-22T11:07:49.334891+00:00",
    "closedAt": null,
    "targetPrice": 90.94282,
    "exitRule": "close on target or invalidation",
    "notes": [
      "auto_managed",
      "alert:entry_ready",
      "live:price=88.205",
      "live:pnlPct=-0.1",
      "live:distanceToInvalidationPct=10.48"
    ]
  },
  {
    "symbol": "XRPUSDT",
    "side": "BUY",
    "timeframe": "4h",
    "status": "open",
    "entryPrice": 1.4497,
    "invalidationPrice": 1.3184,
    "exitPrice": null,
    "resultPct": -0.01,
    "quality": "MEDIUM",
    "openedAt": "2026-04-22T11:22:58.633784+00:00",
    "closedAt": null,
    "targetPrice": 1.493191,
    "exitRule": "close on target or invalidation",
    "notes": [
      "auto_managed",
      "alert:entry_ready",
      "live:price=1.4496",
      "live:pnlPct=-0.01",
      "live:distanceToInvalidationPct=9.05"
    ]
  },
  {
    "symbol": "AAVEUSDT",
    "side": "BUY",
    "timeframe": "4h",
    "status": "open",
    "entryPrice": 93.23,
    "invalidationPrice": 89.4,
    "exitPrice": null,
    "resultPct": 0.01,
    "quality": "GOOD",
    "openedAt": "2026-04-22T11:22:58.633784+00:00",
    "closedAt": null,
    "targetPrice": 96.0269,
    "exitRule": "close on target or invalidation",
    "notes": [
      "auto_managed",
      "alert:entry_ready",
      "live:price=93.242",
      "live:pnlPct=0.01",
      "live:distanceToInvalidationPct=4.12"
    ]
  },
  {
    "symbol": "XMRUSDT",
    "side": "BUY",
    "timeframe": "4h",
    "status": "closed",
    "entryPrice": 379.62,
    "invalidationPrice": 142.7,
    "exitPrice": 118.7,
    "resultPct": -68.73,
    "quality": "MEDIUM",
    "openedAt": "2026-04-22T11:07:49.334891+00:00",
    "closedAt": "2026-04-22T11:07:51.117589+00:00",
    "targetPrice": 391.0086,
    "exitRule": "close on target or invalidation",
    "notes": [
      "auto_managed",
      "alert:entry_ready",
      "live:price=379.65",
      "live:pnlPct=0.01",
      "live:distanceToInvalidationPct=62.41",
      "auto_close:invalidation_break",
      "monitor:close_sent"
    ]
  },
  {
    "symbol": "DOGEUSDT",
    "side": "SELL",
    "timeframe": "4h",
    "status": "open",
    "entryPrice": 0.098099,
    "invalidationPrice": 0.10218,
    "exitPrice": null,
    "resultPct": 0.01,
    "quality": "MEDIUM",
    "openedAt": "2026-04-22T11:22:58.633784+00:00",
    "closedAt": null,
    "targetPrice": 0.095156,
    "exitRule": "close on target or invalidation",
    "notes": [
      "auto_managed",
      "alert:entry_ready",
      "live:price=0.09809",
      "live:pnlPct=0.01",
      "live:distanceToInvalidationPct=4.17"
    ]
  },
  {
    "symbol": "BNBUSDT",
    "side": "BUY",
    "timeframe": "4h",
    "status": "open",
    "entryPrice": 641.79,
    "invalidationPrice": 596.42,
    "exitPrice": null,
    "resultPct": -0.04,
    "quality": "MEDIUM",
    "openedAt": "2026-04-22T11:07:49.334891+00:00",
    "closedAt": null,
    "targetPrice": 661.0437,
    "exitRule": "close on target or invalidation",
    "notes": [
      "auto_managed",
      "alert:entry_ready",
      "live:price=641.55",
      "live:pnlPct=-0.04",
      "live:distanceToInvalidationPct=7.03"
    ]
  },
  {
    "symbol": "TAOUSDT",
    "side": "BUY",
    "timeframe": "4h",
    "status": "open",
    "entryPrice": 247.42,
    "invalidationPrice": 234.3,
    "exitPrice": null,
    "resultPct": -0.21,
    "quality": "GOOD",
    "openedAt": "2026-04-22T11:07:49.334891+00:00",
    "closedAt": null,
    "targetPrice": 254.8426,
    "exitRule": "close on target or invalidation",
    "notes": [
      "auto_managed",
      "alert:entry_ready",
      "live:price=246.91",
      "live:pnlPct=-0.21",
      "live:distanceToInvalidationPct=5.11"
    ]
  },
  {
    "symbol": "SUIUSDT",
    "side": "BUY",
    "timeframe": "4h",
    "status": "open",
    "entryPrice": 0.9731,
    "invalidationPrice": 0.8197,
    "exitPrice": null,
    "resultPct": -0.21,
    "quality": "GOOD",
    "openedAt": "2026-04-22T11:07:49.334891+00:00",
    "closedAt": null,
    "targetPrice": 1.002293,
    "exitRule": "close on target or invalidation",
    "notes": [
      "auto_managed",
      "alert:entry_ready",
      "live:price=0.97104",
      "live:pnlPct=-0.21",
      "live:distanceToInvalidationPct=15.59"
    ]
  },
  {
    "symbol": "ARBUSDT",
    "side": "BUY",
    "timeframe": "4h",
    "status": "open",
    "entryPrice": 0.12842,
    "invalidationPrice": 0.0858,
    "exitPrice": null,
    "resultPct": -0.45,
    "quality": "MEDIUM",
    "openedAt": "2026-04-22T11:07:49.334891+00:00",
    "closedAt": null,
    "targetPrice": 0.132273,
    "exitRule": "close on target or invalidation",
    "notes": [
      "auto_managed",
      "alert:entry_ready",
      "live:price=0.12784",
      "live:pnlPct=-0.45",
      "live:distanceToInvalidationPct=32.88"
    ]
  },
  {
    "symbol": "ZROUSDT",
    "side": "BUY",
    "timeframe": "4h",
    "status": "closed",
    "entryPrice": 1.6253,
    "invalidationPrice": 1.783,
    "exitPrice": 1.6256,
    "resultPct": 0.02,
    "quality": "GOOD",
    "openedAt": "2026-04-22T11:22:58.633784+00:00",
    "closedAt": "2026-04-22T11:22:59.749750+00:00",
    "targetPrice": 1.674059,
    "exitRule": "close on target or invalidation",
    "notes": [
      "auto_managed",
      "alert:entry_ready",
      "live:price=1.6256",
      "live:pnlPct=0.02",
      "live:distanceToInvalidationPct=-9.68",
      "auto_close:invalidation_break",
      "alert:close_sent"
    ]
  },
  {
    "symbol": "AVAXUSDT",
    "side": "BUY",
    "timeframe": "4h",
    "status": "open",
    "entryPrice": 9.5926,
    "invalidationPrice": 8.37,
    "exitPrice": null,
    "resultPct": -0.04,
    "quality": "MEDIUM",
    "openedAt": "2026-04-22T11:07:49.334891+00:00",
    "closedAt": null,
    "targetPrice": 9.880378,
    "exitRule": "close on target or invalidation",
    "notes": [
      "auto_managed",
      "alert:entry_ready",
      "live:price=9.5889",
      "live:pnlPct=-0.04",
      "live:distanceToInvalidationPct=12.71"
    ]
  },
  {
    "symbol": "LINKUSDT",
    "side": "BUY",
    "timeframe": "4h",
    "status": "open",
    "entryPrice": 9.5205,
    "invalidationPrice": 8.37,
    "exitPrice": null,
    "resultPct": -0.12,
    "quality": "MEDIUM",
    "openedAt": "2026-04-22T11:07:49.334891+00:00",
    "closedAt": null,
    "targetPrice": 9.806115,
    "exitRule": "close on target or invalidation",
    "notes": [
      "auto_managed",
      "alert:entry_ready",
      "live:price=9.5093",
      "live:pnlPct=-0.12",
      "live:distanceToInvalidationPct=11.98"
    ]
  },
  {
    "symbol": "NEARUSDT",
    "side": "BUY",
    "timeframe": "4h",
    "status": "open",
    "entryPrice": 1.4228,
    "invalidationPrice": 1.129,
    "exitPrice": null,
    "resultPct": -0.07,
    "quality": "MEDIUM",
    "openedAt": "2026-04-22T11:22:58.633784+00:00",
    "closedAt": null,
    "targetPrice": 1.465484,
    "exitRule": "close on target or invalidation",
    "notes": [
      "auto_managed",
      "alert:entry_ready",
      "live:price=1.4218",
      "live:pnlPct=-0.07",
      "live:distanceToInvalidationPct=20.59"
    ]
  },
  {
    "symbol": "TONUSDT",
    "side": "SELL",
    "timeframe": "4h",
    "status": "closed",
    "entryPrice": 1.3776,
    "invalidationPrice": 1.35,
    "exitPrice": 1.3777,
    "resultPct": -0.01,
    "quality": "GOOD",
    "openedAt": "2026-04-22T11:07:49.334891+00:00",
    "closedAt": "2026-04-22T11:07:50.435085+00:00",
    "targetPrice": 1.336272,
    "exitRule": "close on target or invalidation",
    "notes": [
      "auto_managed",
      "alert:entry_ready",
      "live:price=1.3777",
      "live:pnlPct=-0.01",
      "live:distanceToInvalidationPct=-2.01",
      "auto_close:invalidation_break",
      "alert:close_sent"
    ]
  },
  {
    "symbol": "TRXUSDT",
    "side": "SELL",
    "timeframe": "4h",
    "status": "closed",
    "entryPrice": 0.33335,
    "invalidationPrice": 0.292,
    "exitPrice": 0.33335,
    "resultPct": -0.0,
    "quality": "MEDIUM",
    "openedAt": "2026-04-22T11:07:49.334891+00:00",
    "closedAt": "2026-04-22T11:07:50.435085+00:00",
    "targetPrice": 0.323349,
    "exitRule": "close on target or invalidation",
    "notes": [
      "auto_managed",
      "alert:entry_ready",
      "live:price=0.33335",
      "live:pnlPct=-0.0",
      "live:distanceToInvalidationPct=-12.4",
      "auto_close:invalidation_break",
      "alert:close_sent"
    ]
  },
  {
    "symbol": "UNIUSDT",
    "side": "BUY",
    "timeframe": "4h",
    "status": "open",
    "entryPrice": 3.3815,
    "invalidationPrice": 3.014,
    "exitPrice": null,
    "resultPct": -0.01,
    "quality": "MEDIUM",
    "openedAt": "2026-04-22T11:22:58.633784+00:00",
    "closedAt": null,
    "targetPrice": 3.482945,
    "exitRule": "close on target or invalidation",
    "notes": [
      "auto_managed",
      "alert:entry_ready",
      "live:price=3.3812",
      "live:pnlPct=-0.01",
      "live:distanceToInvalidationPct=10.86"
    ]
  },
  {
    "symbol": "CRVUSDT",
    "side": "BUY",
    "timeframe": "4h",
    "status": "open",
    "entryPrice": 0.23734,
    "invalidationPrice": 0.2061,
    "exitPrice": null,
    "resultPct": -0.41,
    "quality": "MEDIUM",
    "openedAt": "2026-04-22T11:07:49.334891+00:00",
    "closedAt": null,
    "targetPrice": 0.24446,
    "exitRule": "close on target or invalidation",
    "notes": [
      "auto_managed",
      "alert:entry_ready",
      "live:price=0.23637",
      "live:pnlPct=-0.41",
      "live:distanceToInvalidationPct=12.81"
    ]
  },
  {
    "symbol": "WLDUSDT",
    "side": "BUY",
    "timeframe": "4h",
    "status": "open",
    "entryPrice": 0.26804,
    "invalidationPrice": 0.2389,
    "exitPrice": null,
    "resultPct": -0.01,
    "quality": "MEDIUM",
    "openedAt": "2026-04-22T11:22:58.633784+00:00",
    "closedAt": null,
    "targetPrice": 0.276081,
    "exitRule": "close on target or invalidation",
    "notes": [
      "auto_managed",
      "alert:entry_ready",
      "live:price=0.26801",
      "live:pnlPct=-0.01",
      "live:distanceToInvalidationPct=10.86"
    ]
  },
  {
    "symbol": "JUPUSDT",
    "side": "BUY",
    "timeframe": "4h",
    "status": "open",
    "entryPrice": 0.17957,
    "invalidationPrice": 0.1382,
    "exitPrice": null,
    "resultPct": -0.4,
    "quality": "GOOD",
    "openedAt": "2026-04-22T11:07:49.334891+00:00",
    "closedAt": null,
    "targetPrice": 0.184957,
    "exitRule": "close on target or invalidation",
    "notes": [
      "auto_managed",
      "alert:entry_ready",
      "live:price=0.17886",
      "live:pnlPct=-0.4",
      "live:distanceToInvalidationPct=22.73"
    ]
  },
  {
    "symbol": "WIFUSDT",
    "side": "SELL",
    "timeframe": "4h",
    "status": "closed",
    "entryPrice": 0.20158,
    "invalidationPrice": 0.194,
    "exitPrice": 0.20159,
    "resultPct": -0.0,
    "quality": "MEDIUM",
    "openedAt": "2026-04-22T11:07:49.334891+00:00",
    "closedAt": "2026-04-22T11:07:50.435085+00:00",
    "targetPrice": 0.195533,
    "exitRule": "close on target or invalidation",
    "notes": [
      "auto_managed",
      "alert:entry_ready",
      "live:price=0.20159",
      "live:pnlPct=-0.0",
      "live:distanceToInvalidationPct=-3.77",
      "auto_close:invalidation_break",
      "alert:close_sent"
    ]
  },
  {
    "symbol": "RUNEUSDT",
    "side": "BUY",
    "timeframe": "4h",
    "status": "open",
    "entryPrice": 0.49089,
    "invalidationPrice": 0.386,
    "exitPrice": null,
    "resultPct": 0.08,
    "quality": "GOOD",
    "openedAt": "2026-04-22T11:07:49.334891+00:00",
    "closedAt": null,
    "targetPrice": 0.505617,
    "exitRule": "close on target or invalidation",
    "notes": [
      "auto_managed",
      "alert:entry_ready",
      "live:price=0.49129",
      "live:pnlPct=0.08",
      "live:distanceToInvalidationPct=21.43"
    ]
  },
  {
    "symbol": "APTUSDT",
    "side": "BUY",
    "timeframe": "4h",
    "status": "open",
    "entryPrice": 0.9978,
    "invalidationPrice": 0.839,
    "exitPrice": null,
    "resultPct": -0.87,
    "quality": "MEDIUM",
    "openedAt": "2026-04-22T11:07:49.334891+00:00",
    "closedAt": null,
    "targetPrice": 1.027734,
    "exitRule": "close on target or invalidation",
    "notes": [
      "auto_managed",
      "alert:entry_ready",
      "live:price=0.9891",
      "live:pnlPct=-0.87",
      "live:distanceToInvalidationPct=15.18"
    ]
  },
  {
    "symbol": "DOTUSDT",
    "side": "BUY",
    "timeframe": "4h",
    "status": "closed",
    "entryPrice": 1.3116,
    "invalidationPrice": 1.36,
    "exitPrice": 1.3116,
    "resultPct": 0.0,
    "quality": "MEDIUM",
    "openedAt": "2026-04-22T11:07:49.334891+00:00",
    "closedAt": "2026-04-22T11:07:50.435085+00:00",
    "targetPrice": 1.350948,
    "exitRule": "close on target or invalidation",
    "notes": [
      "auto_managed",
      "alert:entry_ready",
      "live:price=1.3116",
      "live:pnlPct=0.0",
      "live:distanceToInvalidationPct=-3.69",
      "auto_close:invalidation_break",
      "alert:close_sent"
    ]
  },
  {
    "symbol": "HBARUSDT",
    "side": "BUY",
    "timeframe": "4h",
    "status": "open",
    "entryPrice": 0.09109,
    "invalidationPrice": 0.08603,
    "exitPrice": null,
    "resultPct": 0.0,
    "quality": "MEDIUM",
    "openedAt": "2026-04-22T11:22:58.633784+00:00",
    "closedAt": null,
    "targetPrice": 0.093823,
    "exitRule": "close on target or invalidation",
    "notes": [
      "auto_managed",
      "alert:entry_ready",
      "live:price=0.09109",
      "live:pnlPct=0.0",
      "live:distanceToInvalidationPct=5.55"
    ]
  }
]