{
  "updatedAt": "2026-05-06T19:00:34.200599+00:00",
  "rows": [
    {
      "symbol": "AAVEUSDT",
      "livePrice": 93.195,
      "entryPrice": null,
      "invalidationPrice": null,
      "side": null,
      "livePnlPct": null,
      "distanceToInvalidationPct": null,
      "marketTimestamp": "2026-05-06T19:00:34.200599+00:00",
      "sourceVenue": "hyper"
    },
    {
      "symbol": "ADAUSDT",
      "livePrice": 0.26607,
      "entryPrice": null,
      "invalidationPrice": null,
      "side": null,
      "livePnlPct": null,
      "distanceToInvalidationPct": null,
      "marketTimestamp": "2026-05-06T19:00:34.200599+00:00",
      "sourceVenue": "hyper"
    },
    {
      "symbol": "AEROUSDT",
      "livePrice": 0.46196,
      "entryPrice": null,
      "invalidationPrice": null,
      "side": null,
      "livePnlPct": null,
      "distanceToInvalidationPct": null,
      "marketTimestamp": "2026-05-06T19:00:34.200599+00:00",
      "sourceVenue": "hyper"
    },
    {
      "symbol": "APTUSDT",
      "livePrice": 1.0143,
      "entryPrice": null,
      "invalidationPrice": null,
      "side": null,
      "livePnlPct": null,
      "distanceToInvalidationPct": null,
      "marketTimestamp": "2026-05-06T19:00:34.200599+00:00",
      "sourceVenue": "hyper"
    },
    {
      "symbol": "ARBUSDT",
      "livePrice": 0.12338,
      "entryPrice": null,
      "invalidationPrice": null,
      "side": null,
      "livePnlPct": null,
      "distanceToInvalidationPct": null,
      "marketTimestamp": "2026-05-06T19:00:34.200599+00:00",
      "sourceVenue": "hyper"
    },
    {
      "symbol": "AVAXUSDT",
      "livePrice": 9.5847,
      "entryPrice": null,
      "invalidationPrice": null,
      "side": null,
      "livePnlPct": null,
      "distanceToInvalidationPct": null,
      "marketTimestamp": "2026-05-06T19:00:34.200599+00:00",
      "sourceVenue": "hyper"
    },
    {
      "symbol": "BCHUSDT",
      "livePrice": 465.29,
      "entryPrice": null,
      "invalidationPrice": null,
      "side": null,
      "livePnlPct": null,
      "distanceToInvalidationPct": null,
      "marketTimestamp": "2026-05-06T19:00:34.200599+00:00",
      "sourceVenue": "hyper"
    },
    {
      "symbol": "BNBUSDT",
      "livePrice": 649.9,
      "entryPrice": null,
      "invalidationPrice": null,
      "side": null,
      "livePnlPct": null,
      "distanceToInvalidationPct": null,
      "marketTimestamp": "2026-05-06T19:00:34.200599+00:00",
      "sourceVenue": "hyper"
    },
    {
      "symbol": "BTCUSDT",
      "livePrice": 81327.0,
      "entryPrice": null,
      "invalidationPrice": null,
      "side": null,
      "livePnlPct": null,
      "distanceToInvalidationPct": null,
      "marketTimestamp": "2026-05-06T19:00:34.200599+00:00",
      "sourceVenue": "hyper"
    },
    {
      "symbol": "CRVUSDT",
      "livePrice": 0.245,
      "entryPrice": null,
      "invalidationPrice": null,
      "side": null,
      "livePnlPct": null,
      "distanceToInvalidationPct": null,
      "marketTimestamp": "2026-05-06T19:00:34.200599+00:00",
      "sourceVenue": "hyper"
    },
    {
      "symbol": "DOGEUSDT",
      "livePrice": 0.1128,
      "entryPrice": null,
      "invalidationPrice": null,
      "side": null,
      "livePnlPct": null,
      "distanceToInvalidationPct": null,
      "marketTimestamp": "2026-05-06T19:00:34.200599+00:00",
      "sourceVenue": "hyper"
    },
    {
      "symbol": "DOTUSDT",
      "livePrice": 1.3055,
      "entryPrice": null,
      "invalidationPrice": null,
      "side": null,
      "livePnlPct": null,
      "distanceToInvalidationPct": null,
      "marketTimestamp": "2026-05-06T19:00:34.200599+00:00",
      "sourceVenue": "hyper"
    },
    {
      "symbol": "ETHUSDT",
      "livePrice": 2344.6,
      "entryPrice": null,
      "invalidationPrice": null,
      "side": null,
      "livePnlPct": null,
      "distanceToInvalidationPct": null,
      "marketTimestamp": "2026-05-06T19:00:34.200599+00:00",
      "sourceVenue": "hyper"
    },
    {
      "symbol": "HBARUSDT",
      "livePrice": 0.091316,
      "entryPrice": null,
      "invalidationPrice": null,
      "side": null,
      "livePnlPct": null,
      "distanceToInvalidationPct": null,
      "marketTimestamp": "2026-05-06T19:00:34.200599+00:00",
      "sourceVenue": "hyper"
    },
    {
      "symbol": "JUPUSDT",
      "livePrice": 0.19734,
      "entryPrice": null,
      "invalidationPrice": null,
      "side": null,
      "livePnlPct": null,
      "distanceToInvalidationPct": null,
      "marketTimestamp": "2026-05-06T19:00:34.200599+00:00",
      "sourceVenue": "hyper"
    },
    {
      "symbol": "LINKUSDT",
      "livePrice": 9.9662,
      "entryPrice": null,
      "invalidationPrice": null,
      "side": null,
      "livePnlPct": null,
      "distanceToInvalidationPct": null,
      "marketTimestamp": "2026-05-06T19:00:34.200599+00:00",
      "sourceVenue": "hyper"
    },
    {
      "symbol": "LTCUSDT",
      "livePrice": 56.839,
      "entryPrice": null,
      "invalidationPrice": null,
      "side": null,
      "livePnlPct": null,
      "distanceToInvalidationPct": null,
      "marketTimestamp": "2026-05-06T19:00:34.200599+00:00",
      "sourceVenue": "hyper"
    },
    {
      "symbol": "NEARUSDT",
      "livePrice": 1.5,
      "entryPrice": null,
      "invalidationPrice": null,
      "side": null,
      "livePnlPct": null,
      "distanceToInvalidationPct": null,
      "marketTimestamp": "2026-05-06T19:00:34.200599+00:00",
      "sourceVenue": "hyper"
    },
    {
      "symbol": "RUNEUSDT",
      "livePrice": 0.55671,
      "entryPrice": null,
      "invalidationPrice": null,
      "side": null,
      "livePnlPct": null,
      "distanceToInvalidationPct": null,
      "marketTimestamp": "2026-05-06T19:00:34.200599+00:00",
      "sourceVenue": "hyper"
    },
    {
      "symbol": "SOLUSDT",
      "livePrice": 88.968,
      "entryPrice": null,
      "invalidationPrice": null,
      "side": null,
      "livePnlPct": null,
      "distanceToInvalidationPct": null,
      "marketTimestamp": "2026-05-06T19:00:34.200599+00:00",
      "sourceVenue": "hyper"
    },
    {
      "symbol": "SUIUSDT",
      "livePrice": 0.98876,
      "entryPrice": null,
      "invalidationPrice": null,
      "side": null,
      "livePnlPct": null,
      "distanceToInvalidationPct": null,
      "marketTimestamp": "2026-05-06T19:00:34.200599+00:00",
      "sourceVenue": "hyper"
    },
    {
      "symbol": "TAOUSDT",
      "livePrice": 314.75,
      "entryPrice": null,
      "invalidationPrice": null,
      "side": null,
      "livePnlPct": null,
      "distanceToInvalidationPct": null,
      "marketTimestamp": "2026-05-06T19:00:34.200599+00:00",
      "sourceVenue": "hyper"
    },
    {
      "symbol": "TONUSDT",
      "livePrice": 2.4099,
      "entryPrice": null,
      "invalidationPrice": null,
      "side": null,
      "livePnlPct": null,
      "distanceToInvalidationPct": null,
      "marketTimestamp": "2026-05-06T19:00:34.200599+00:00",
      "sourceVenue": "hyper"
    },
    {
      "symbol": "TRXUSDT",
      "livePrice": 0.3468,
      "entryPrice": null,
      "invalidationPrice": null,
      "side": null,
      "livePnlPct": null,
      "distanceToInvalidationPct": null,
      "marketTimestamp": "2026-05-06T19:00:34.200599+00:00",
      "sourceVenue": "hyper"
    },
    {
      "symbol": "UNIUSDT",
      "livePrice": 3.4522,
      "entryPrice": null,
      "invalidationPrice": null,
      "side": null,
      "livePnlPct": null,
      "distanceToInvalidationPct": null,
      "marketTimestamp": "2026-05-06T19:00:34.200599+00:00",
      "sourceVenue": "hyper"
    },
    {
      "symbol": "WIFUSDT",
      "livePrice": 0.22282,
      "entryPrice": null,
      "invalidationPrice": null,
      "side": null,
      "livePnlPct": null,
      "distanceToInvalidationPct": null,
      "marketTimestamp": "2026-05-06T19:00:34.200599+00:00",
      "sourceVenue": "hyper"
    },
    {
      "symbol": "WLDUSDT",
      "livePrice": 0.2549,
      "entryPrice": null,
      "invalidationPrice": null,
      "side": null,
      "livePnlPct": null,
      "distanceToInvalidationPct": null,
      "marketTimestamp": "2026-05-06T19:00:34.200599+00:00",
      "sourceVenue": "hyper"
    },
    {
      "symbol": "XMRUSDT",
      "livePrice": 411.49,
      "entryPrice": null,
      "invalidationPrice": null,
      "side": null,
      "livePnlPct": null,
      "distanceToInvalidationPct": null,
      "marketTimestamp": "2026-05-06T19:00:34.200599+00:00",
      "sourceVenue": "hyper"
    },
    {
      "symbol": "XRPUSDT",
      "livePrice": 1.4224,
      "entryPrice": null,
      "invalidationPrice": null,
      "side": null,
      "livePnlPct": null,
      "distanceToInvalidationPct": null,
      "marketTimestamp": "2026-05-06T19:00:34.200599+00:00",
      "sourceVenue": "hyper"
    },
    {
      "symbol": "ZROUSDT",
      "livePrice": 1.5187,
      "entryPrice": null,
      "invalidationPrice": null,
      "side": null,
      "livePnlPct": null,
      "distanceToInvalidationPct": null,
      "marketTimestamp": "2026-05-06T19:00:34.200599+00:00",
      "sourceVenue": "hyper"
    }
  ]
}