{
  "updatedAt": "2026-05-12T02:00:35.932956+00:00",
  "rows": [
    {
      "symbol": "AAVEUSDT",
      "livePrice": 99.549,
      "entryPrice": null,
      "invalidationPrice": null,
      "side": null,
      "livePnlPct": null,
      "distanceToInvalidationPct": null,
      "marketTimestamp": "2026-05-12T02:00:35.932956+00:00",
      "sourceVenue": "hyper"
    },
    {
      "symbol": "ADAUSDT",
      "livePrice": 0.27742,
      "entryPrice": null,
      "invalidationPrice": null,
      "side": null,
      "livePnlPct": null,
      "distanceToInvalidationPct": null,
      "marketTimestamp": "2026-05-12T02:00:35.932956+00:00",
      "sourceVenue": "hyper"
    },
    {
      "symbol": "AEROUSDT",
      "livePrice": 0.52061,
      "entryPrice": null,
      "invalidationPrice": null,
      "side": null,
      "livePnlPct": null,
      "distanceToInvalidationPct": null,
      "marketTimestamp": "2026-05-12T02:00:35.932956+00:00",
      "sourceVenue": "hyper"
    },
    {
      "symbol": "APTUSDT",
      "livePrice": 1.1027,
      "entryPrice": null,
      "invalidationPrice": null,
      "side": null,
      "livePnlPct": null,
      "distanceToInvalidationPct": null,
      "marketTimestamp": "2026-05-12T02:00:35.932956+00:00",
      "sourceVenue": "hyper"
    },
    {
      "symbol": "ARBUSDT",
      "livePrice": 0.13885,
      "entryPrice": null,
      "invalidationPrice": null,
      "side": null,
      "livePnlPct": null,
      "distanceToInvalidationPct": null,
      "marketTimestamp": "2026-05-12T02:00:35.932956+00:00",
      "sourceVenue": "hyper"
    },
    {
      "symbol": "AVAXUSDT",
      "livePrice": 10.023,
      "entryPrice": null,
      "invalidationPrice": null,
      "side": null,
      "livePnlPct": null,
      "distanceToInvalidationPct": null,
      "marketTimestamp": "2026-05-12T02:00:35.932956+00:00",
      "sourceVenue": "hyper"
    },
    {
      "symbol": "BCHUSDT",
      "livePrice": 443.52,
      "entryPrice": null,
      "invalidationPrice": null,
      "side": null,
      "livePnlPct": null,
      "distanceToInvalidationPct": null,
      "marketTimestamp": "2026-05-12T02:00:35.932956+00:00",
      "sourceVenue": "hyper"
    },
    {
      "symbol": "BNBUSDT",
      "livePrice": 663.2,
      "entryPrice": null,
      "invalidationPrice": null,
      "side": null,
      "livePnlPct": null,
      "distanceToInvalidationPct": null,
      "marketTimestamp": "2026-05-12T02:00:35.932956+00:00",
      "sourceVenue": "hyper"
    },
    {
      "symbol": "BTCUSDT",
      "livePrice": 81139.0,
      "entryPrice": null,
      "invalidationPrice": null,
      "side": null,
      "livePnlPct": null,
      "distanceToInvalidationPct": null,
      "marketTimestamp": "2026-05-12T02:00:35.932956+00:00",
      "sourceVenue": "hyper"
    },
    {
      "symbol": "CRVUSDT",
      "livePrice": 0.28156,
      "entryPrice": null,
      "invalidationPrice": null,
      "side": null,
      "livePnlPct": null,
      "distanceToInvalidationPct": null,
      "marketTimestamp": "2026-05-12T02:00:35.932956+00:00",
      "sourceVenue": "hyper"
    },
    {
      "symbol": "DOGEUSDT",
      "livePrice": 0.11092,
      "entryPrice": null,
      "invalidationPrice": null,
      "side": null,
      "livePnlPct": null,
      "distanceToInvalidationPct": null,
      "marketTimestamp": "2026-05-12T02:00:35.932956+00:00",
      "sourceVenue": "hyper"
    },
    {
      "symbol": "DOTUSDT",
      "livePrice": 1.3496,
      "entryPrice": null,
      "invalidationPrice": null,
      "side": null,
      "livePnlPct": null,
      "distanceToInvalidationPct": null,
      "marketTimestamp": "2026-05-12T02:00:35.932956+00:00",
      "sourceVenue": "hyper"
    },
    {
      "symbol": "ETHUSDT",
      "livePrice": 2309.6,
      "entryPrice": null,
      "invalidationPrice": null,
      "side": null,
      "livePnlPct": null,
      "distanceToInvalidationPct": null,
      "marketTimestamp": "2026-05-12T02:00:35.932956+00:00",
      "sourceVenue": "hyper"
    },
    {
      "symbol": "HBARUSDT",
      "livePrice": 0.095626,
      "entryPrice": null,
      "invalidationPrice": null,
      "side": null,
      "livePnlPct": null,
      "distanceToInvalidationPct": null,
      "marketTimestamp": "2026-05-12T02:00:35.932956+00:00",
      "sourceVenue": "hyper"
    },
    {
      "symbol": "JUPUSDT",
      "livePrice": 0.24427,
      "entryPrice": null,
      "invalidationPrice": null,
      "side": null,
      "livePnlPct": null,
      "distanceToInvalidationPct": null,
      "marketTimestamp": "2026-05-12T02:00:35.932956+00:00",
      "sourceVenue": "hyper"
    },
    {
      "symbol": "LINKUSDT",
      "livePrice": 10.471,
      "entryPrice": null,
      "invalidationPrice": null,
      "side": null,
      "livePnlPct": null,
      "distanceToInvalidationPct": null,
      "marketTimestamp": "2026-05-12T02:00:35.932956+00:00",
      "sourceVenue": "hyper"
    },
    {
      "symbol": "LTCUSDT",
      "livePrice": 57.873,
      "entryPrice": null,
      "invalidationPrice": null,
      "side": null,
      "livePnlPct": null,
      "distanceToInvalidationPct": null,
      "marketTimestamp": "2026-05-12T02:00:35.932956+00:00",
      "sourceVenue": "hyper"
    },
    {
      "symbol": "NEARUSDT",
      "livePrice": 1.5116,
      "entryPrice": null,
      "invalidationPrice": null,
      "side": null,
      "livePnlPct": null,
      "distanceToInvalidationPct": null,
      "marketTimestamp": "2026-05-12T02:00:35.932956+00:00",
      "sourceVenue": "hyper"
    },
    {
      "symbol": "RUNEUSDT",
      "livePrice": 0.6149,
      "entryPrice": null,
      "invalidationPrice": null,
      "side": null,
      "livePnlPct": null,
      "distanceToInvalidationPct": null,
      "marketTimestamp": "2026-05-12T02:00:35.932956+00:00",
      "sourceVenue": "hyper"
    },
    {
      "symbol": "SOLUSDT",
      "livePrice": 96.221,
      "entryPrice": null,
      "invalidationPrice": null,
      "side": null,
      "livePnlPct": null,
      "distanceToInvalidationPct": null,
      "marketTimestamp": "2026-05-12T02:00:35.932956+00:00",
      "sourceVenue": "hyper"
    },
    {
      "symbol": "SUIUSDT",
      "livePrice": 1.2716,
      "entryPrice": null,
      "invalidationPrice": null,
      "side": null,
      "livePnlPct": null,
      "distanceToInvalidationPct": null,
      "marketTimestamp": "2026-05-12T02:00:35.932956+00:00",
      "sourceVenue": "hyper"
    },
    {
      "symbol": "TAOUSDT",
      "livePrice": 316.82,
      "entryPrice": null,
      "invalidationPrice": null,
      "side": null,
      "livePnlPct": null,
      "distanceToInvalidationPct": null,
      "marketTimestamp": "2026-05-12T02:00:35.932956+00:00",
      "sourceVenue": "hyper"
    },
    {
      "symbol": "TONUSDT",
      "livePrice": 2.3878,
      "entryPrice": null,
      "invalidationPrice": null,
      "side": null,
      "livePnlPct": null,
      "distanceToInvalidationPct": null,
      "marketTimestamp": "2026-05-12T02:00:35.932956+00:00",
      "sourceVenue": "hyper"
    },
    {
      "symbol": "TRXUSDT",
      "livePrice": 0.35038,
      "entryPrice": null,
      "invalidationPrice": null,
      "side": null,
      "livePnlPct": null,
      "distanceToInvalidationPct": null,
      "marketTimestamp": "2026-05-12T02:00:35.932956+00:00",
      "sourceVenue": "hyper"
    },
    {
      "symbol": "UNIUSDT",
      "livePrice": 3.8052,
      "entryPrice": null,
      "invalidationPrice": null,
      "side": null,
      "livePnlPct": null,
      "distanceToInvalidationPct": null,
      "marketTimestamp": "2026-05-12T02:00:35.932956+00:00",
      "sourceVenue": "hyper"
    },
    {
      "symbol": "WIFUSDT",
      "livePrice": 0.22605,
      "entryPrice": null,
      "invalidationPrice": null,
      "side": null,
      "livePnlPct": null,
      "distanceToInvalidationPct": null,
      "marketTimestamp": "2026-05-12T02:00:35.932956+00:00",
      "sourceVenue": "hyper"
    },
    {
      "symbol": "WLDUSDT",
      "livePrice": 0.27487,
      "entryPrice": null,
      "invalidationPrice": null,
      "side": null,
      "livePnlPct": null,
      "distanceToInvalidationPct": null,
      "marketTimestamp": "2026-05-12T02:00:35.932956+00:00",
      "sourceVenue": "hyper"
    },
    {
      "symbol": "XMRUSDT",
      "livePrice": 412.88,
      "entryPrice": null,
      "invalidationPrice": null,
      "side": null,
      "livePnlPct": null,
      "distanceToInvalidationPct": null,
      "marketTimestamp": "2026-05-12T02:00:35.932956+00:00",
      "sourceVenue": "hyper"
    },
    {
      "symbol": "XRPUSDT",
      "livePrice": 1.4659,
      "entryPrice": null,
      "invalidationPrice": null,
      "side": null,
      "livePnlPct": null,
      "distanceToInvalidationPct": null,
      "marketTimestamp": "2026-05-12T02:00:35.932956+00:00",
      "sourceVenue": "hyper"
    },
    {
      "symbol": "ZROUSDT",
      "livePrice": 1.508,
      "entryPrice": null,
      "invalidationPrice": null,
      "side": null,
      "livePnlPct": null,
      "distanceToInvalidationPct": null,
      "marketTimestamp": "2026-05-12T02:00:35.932956+00:00",
      "sourceVenue": "hyper"
    }
  ]
}