{
  "strategy": "DiverT Strategy",
  "updatedAt": "2026-05-02T06:00:37.026640+00:00",
  "lastScan": {
    "status": "success",
    "newSignals": 2,
    "nextScanAt": "2026-05-02T06:30:37.026640+00:00"
  },
  "rows": [
    {
      "symbol": "BTCUSDT",
      "signal": "NO",
      "side": "NONE",
      "quality": "FRAGILE",
      "invalidation": null,
      "scanPrice": 78161.0,
      "sourceVenue": "hyper",
      "notes": [
        "Nu exista inca o structura DiverT valida pe buy sau sell",
        "price_now=78161.0"
      ],
      "patternContext": "neutral",
      "entryStructure": "no_valid_divert_v0_3_signal",
      "risk": "high",
      "timeframe": "4h",
      "execution": {
        "status": "none",
        "entry": "no action",
        "invalidation": null,
        "exitTrigger": "none",
        "closeRule": "none"
      },
      "setupKey": null,
      "setupIndex": null,
      "setupTimestamp": null,
      "setupState": "idle"
    },
    {
      "symbol": "ETHUSDT",
      "signal": "NO",
      "side": "NONE",
      "quality": "FRAGILE",
      "invalidation": null,
      "scanPrice": 2298.5,
      "sourceVenue": "hyper",
      "notes": [
        "Nu exista inca o structura DiverT valida pe buy sau sell",
        "price_now=2298.5"
      ],
      "patternContext": "neutral",
      "entryStructure": "no_valid_divert_v0_3_signal",
      "risk": "high",
      "timeframe": "4h",
      "execution": {
        "status": "none",
        "entry": "no action",
        "invalidation": null,
        "exitTrigger": "none",
        "closeRule": "none"
      },
      "setupKey": null,
      "setupIndex": null,
      "setupTimestamp": null,
      "setupState": "idle"
    },
    {
      "symbol": "SOLUSDT",
      "signal": "NO",
      "side": "NONE",
      "quality": "FRAGILE",
      "invalidation": null,
      "scanPrice": 83.661,
      "sourceVenue": "hyper",
      "notes": [
        "Nu exista inca o structura DiverT valida pe buy sau sell",
        "price_now=83.661"
      ],
      "patternContext": "neutral",
      "entryStructure": "no_valid_divert_v0_3_signal",
      "risk": "high",
      "timeframe": "4h",
      "execution": {
        "status": "none",
        "entry": "no action",
        "invalidation": null,
        "exitTrigger": "none",
        "closeRule": "none"
      },
      "setupKey": null,
      "setupIndex": null,
      "setupTimestamp": null,
      "setupState": "idle"
    },
    {
      "symbol": "XRPUSDT",
      "signal": "NO",
      "side": "NONE",
      "quality": "FRAGILE",
      "invalidation": null,
      "scanPrice": 1.383,
      "sourceVenue": "hyper",
      "notes": [
        "Nu exista inca o structura DiverT valida pe buy sau sell",
        "price_now=1.383"
      ],
      "patternContext": "neutral",
      "entryStructure": "no_valid_divert_v0_3_signal",
      "risk": "high",
      "timeframe": "4h",
      "execution": {
        "status": "none",
        "entry": "no action",
        "invalidation": null,
        "exitTrigger": "none",
        "closeRule": "none"
      },
      "setupKey": null,
      "setupIndex": null,
      "setupTimestamp": null,
      "setupState": "idle"
    },
    {
      "symbol": "AAVEUSDT",
      "signal": "NO",
      "side": "NONE",
      "quality": "FRAGILE",
      "invalidation": null,
      "scanPrice": 91.764,
      "sourceVenue": "hyper",
      "notes": [
        "Nu exista inca o structura DiverT valida pe buy sau sell",
        "price_now=91.764"
      ],
      "patternContext": "neutral",
      "entryStructure": "no_valid_divert_v0_3_signal",
      "risk": "high",
      "timeframe": "4h",
      "execution": {
        "status": "none",
        "entry": "no action",
        "invalidation": null,
        "exitTrigger": "none",
        "closeRule": "none"
      },
      "setupKey": null,
      "setupIndex": null,
      "setupTimestamp": null,
      "setupState": "idle"
    },
    {
      "symbol": "XMRUSDT",
      "signal": "NO",
      "side": "NONE",
      "quality": "FRAGILE",
      "invalidation": null,
      "scanPrice": 384.35,
      "sourceVenue": "hyper",
      "notes": [
        "Nu exista inca o structura DiverT valida pe buy sau sell",
        "price_now=384.35"
      ],
      "patternContext": "neutral",
      "entryStructure": "no_valid_divert_v0_3_signal",
      "risk": "high",
      "timeframe": "4h",
      "execution": {
        "status": "none",
        "entry": "no action",
        "invalidation": null,
        "exitTrigger": "none",
        "closeRule": "none"
      },
      "setupKey": null,
      "setupIndex": null,
      "setupTimestamp": null,
      "setupState": "idle"
    },
    {
      "symbol": "DOGEUSDT",
      "signal": "NO",
      "side": "NONE",
      "quality": "FRAGILE",
      "invalidation": null,
      "scanPrice": 0.1075,
      "sourceVenue": "hyper",
      "notes": [
        "Nu exista inca o structura DiverT valida pe buy sau sell",
        "price_now=0.1075"
      ],
      "patternContext": "neutral",
      "entryStructure": "no_valid_divert_v0_3_signal",
      "risk": "high",
      "timeframe": "4h",
      "execution": {
        "status": "none",
        "entry": "no action",
        "invalidation": null,
        "exitTrigger": "none",
        "closeRule": "none"
      },
      "setupKey": null,
      "setupIndex": null,
      "setupTimestamp": null,
      "setupState": "idle"
    },
    {
      "symbol": "BNBUSDT",
      "signal": "NO",
      "side": "NONE",
      "quality": "FRAGILE",
      "invalidation": null,
      "scanPrice": 614.96,
      "sourceVenue": "hyper",
      "notes": [
        "Nu exista inca o structura DiverT valida pe buy sau sell",
        "price_now=614.96"
      ],
      "patternContext": "neutral",
      "entryStructure": "no_valid_divert_v0_3_signal",
      "risk": "high",
      "timeframe": "4h",
      "execution": {
        "status": "none",
        "entry": "no action",
        "invalidation": null,
        "exitTrigger": "none",
        "closeRule": "none"
      },
      "setupKey": null,
      "setupIndex": null,
      "setupTimestamp": null,
      "setupState": "idle"
    },
    {
      "symbol": "TAOUSDT",
      "signal": "NO",
      "side": "NONE",
      "quality": "FRAGILE",
      "invalidation": null,
      "scanPrice": 271.31,
      "sourceVenue": "hyper",
      "notes": [
        "Nu exista inca o structura DiverT valida pe buy sau sell",
        "price_now=271.31"
      ],
      "patternContext": "positive",
      "entryStructure": "no_valid_divert_v0_3_signal",
      "risk": "high",
      "timeframe": "4h",
      "execution": {
        "status": "none",
        "entry": "no action",
        "invalidation": null,
        "exitTrigger": "none",
        "closeRule": "none"
      },
      "setupKey": null,
      "setupIndex": null,
      "setupTimestamp": null,
      "setupState": "idle"
    },
    {
      "symbol": "SUIUSDT",
      "signal": "NO",
      "side": "NONE",
      "quality": "FRAGILE",
      "invalidation": null,
      "scanPrice": 0.91601,
      "sourceVenue": "hyper",
      "notes": [
        "Nu exista inca o structura DiverT valida pe buy sau sell",
        "price_now=0.91601"
      ],
      "patternContext": "neutral",
      "entryStructure": "no_valid_divert_v0_3_signal",
      "risk": "high",
      "timeframe": "4h",
      "execution": {
        "status": "none",
        "entry": "no action",
        "invalidation": null,
        "exitTrigger": "none",
        "closeRule": "none"
      },
      "setupKey": null,
      "setupIndex": null,
      "setupTimestamp": null,
      "setupState": "idle"
    },
    {
      "symbol": "ARBUSDT",
      "signal": "NO",
      "side": "NONE",
      "quality": "FRAGILE",
      "invalidation": null,
      "scanPrice": 0.12212,
      "sourceVenue": "hyper",
      "notes": [
        "Nu exista inca o structura DiverT valida pe buy sau sell",
        "price_now=0.12212"
      ],
      "patternContext": "neutral",
      "entryStructure": "no_valid_divert_v0_3_signal",
      "risk": "high",
      "timeframe": "4h",
      "execution": {
        "status": "none",
        "entry": "no action",
        "invalidation": null,
        "exitTrigger": "none",
        "closeRule": "none"
      },
      "setupKey": null,
      "setupIndex": null,
      "setupTimestamp": null,
      "setupState": "idle"
    },
    {
      "symbol": "ZROUSDT",
      "signal": "WATCH",
      "side": "BUY",
      "quality": "GOOD",
      "invalidation": 1.397,
      "scanPrice": 1.3763,
      "sourceVenue": "hyper",
      "notes": [
        "Buy DiverT setup valid",
        "Prima structura valida peste 30 confirmata",
        "Invalidarea defensiva este low-ul setupului",
        "price_now=1.3763",
        "same_side_blocked_48h"
      ],
      "patternContext": "neutral",
      "entryStructure": "buy_divert_v0_3",
      "risk": "medium",
      "timeframe": "4h",
      "execution": {
        "status": "cooldown_active",
        "entry": "same-side setup blocked during 48h cooldown",
        "invalidation": 1.397,
        "exitTrigger": "wait for cooldown expiry or new structure",
        "closeRule": "none"
      },
      "setupKey": "buy:276:284:272:284",
      "setupIndex": 284,
      "setupTimestamp": "2026-04-29T16:00:00+00:00",
      "setupState": "cooldown"
    },
    {
      "symbol": "AVAXUSDT",
      "signal": "NO",
      "side": "NONE",
      "quality": "FRAGILE",
      "invalidation": null,
      "scanPrice": 9.0772,
      "sourceVenue": "hyper",
      "notes": [
        "Nu exista inca o structura DiverT valida pe buy sau sell",
        "price_now=9.0772"
      ],
      "patternContext": "neutral",
      "entryStructure": "no_valid_divert_v0_3_signal",
      "risk": "high",
      "timeframe": "4h",
      "execution": {
        "status": "none",
        "entry": "no action",
        "invalidation": null,
        "exitTrigger": "none",
        "closeRule": "none"
      },
      "setupKey": null,
      "setupIndex": null,
      "setupTimestamp": null,
      "setupState": "idle"
    },
    {
      "symbol": "LINKUSDT",
      "signal": "NO",
      "side": "NONE",
      "quality": "FRAGILE",
      "invalidation": null,
      "scanPrice": 9.0789,
      "sourceVenue": "hyper",
      "notes": [
        "Nu exista inca o structura DiverT valida pe buy sau sell",
        "price_now=9.0789"
      ],
      "patternContext": "neutral",
      "entryStructure": "no_valid_divert_v0_3_signal",
      "risk": "high",
      "timeframe": "4h",
      "execution": {
        "status": "none",
        "entry": "no action",
        "invalidation": null,
        "exitTrigger": "none",
        "closeRule": "none"
      },
      "setupKey": null,
      "setupIndex": null,
      "setupTimestamp": null,
      "setupState": "idle"
    },
    {
      "symbol": "ADAUSDT",
      "signal": "NO",
      "side": "NONE",
      "quality": "FRAGILE",
      "invalidation": null,
      "scanPrice": 0.24696,
      "sourceVenue": "hyper",
      "notes": [
        "Nu exista inca o structura DiverT valida pe buy sau sell",
        "price_now=0.24696"
      ],
      "patternContext": "neutral",
      "entryStructure": "no_valid_divert_v0_3_signal",
      "risk": "high",
      "timeframe": "4h",
      "execution": {
        "status": "none",
        "entry": "no action",
        "invalidation": null,
        "exitTrigger": "none",
        "closeRule": "none"
      },
      "setupKey": null,
      "setupIndex": null,
      "setupTimestamp": null,
      "setupState": "idle"
    },
    {
      "symbol": "NEARUSDT",
      "signal": "NO",
      "side": "NONE",
      "quality": "FRAGILE",
      "invalidation": null,
      "scanPrice": 1.2871,
      "sourceVenue": "hyper",
      "notes": [
        "Nu exista inca o structura DiverT valida pe buy sau sell",
        "price_now=1.2871"
      ],
      "patternContext": "neutral",
      "entryStructure": "no_valid_divert_v0_3_signal",
      "risk": "high",
      "timeframe": "4h",
      "execution": {
        "status": "none",
        "entry": "no action",
        "invalidation": null,
        "exitTrigger": "none",
        "closeRule": "none"
      },
      "setupKey": null,
      "setupIndex": null,
      "setupTimestamp": null,
      "setupState": "idle"
    },
    {
      "symbol": "BCHUSDT",
      "signal": "NO",
      "side": "NONE",
      "quality": "FRAGILE",
      "invalidation": null,
      "scanPrice": 449.59,
      "sourceVenue": "hyper",
      "notes": [
        "Nu exista inca o structura DiverT valida pe buy sau sell",
        "price_now=449.59"
      ],
      "patternContext": "neutral",
      "entryStructure": "no_valid_divert_v0_3_signal",
      "risk": "high",
      "timeframe": "4h",
      "execution": {
        "status": "none",
        "entry": "no action",
        "invalidation": null,
        "exitTrigger": "none",
        "closeRule": "none"
      },
      "setupKey": null,
      "setupIndex": null,
      "setupTimestamp": null,
      "setupState": "idle"
    },
    {
      "symbol": "TONUSDT",
      "signal": "NO",
      "side": "NONE",
      "quality": "FRAGILE",
      "invalidation": null,
      "scanPrice": 1.3203,
      "sourceVenue": "hyper",
      "notes": [
        "Nu exista inca o structura DiverT valida pe buy sau sell",
        "price_now=1.3203"
      ],
      "patternContext": "neutral",
      "entryStructure": "no_valid_divert_v0_3_signal",
      "risk": "high",
      "timeframe": "4h",
      "execution": {
        "status": "none",
        "entry": "no action",
        "invalidation": null,
        "exitTrigger": "none",
        "closeRule": "none"
      },
      "setupKey": null,
      "setupIndex": null,
      "setupTimestamp": null,
      "setupState": "idle"
    },
    {
      "symbol": "TRXUSDT",
      "signal": "NO",
      "side": "NONE",
      "quality": "FRAGILE",
      "invalidation": null,
      "scanPrice": 0.32883,
      "sourceVenue": "hyper",
      "notes": [
        "Nu exista inca o structura DiverT valida pe buy sau sell",
        "price_now=0.32883"
      ],
      "patternContext": "neutral",
      "entryStructure": "no_valid_divert_v0_3_signal",
      "risk": "high",
      "timeframe": "4h",
      "execution": {
        "status": "none",
        "entry": "no action",
        "invalidation": null,
        "exitTrigger": "none",
        "closeRule": "none"
      },
      "setupKey": null,
      "setupIndex": null,
      "setupTimestamp": null,
      "setupState": "idle"
    },
    {
      "symbol": "UNIUSDT",
      "signal": "NO",
      "side": "NONE",
      "quality": "FRAGILE",
      "invalidation": null,
      "scanPrice": 3.199,
      "sourceVenue": "hyper",
      "notes": [
        "Nu exista inca o structura DiverT valida pe buy sau sell",
        "price_now=3.199"
      ],
      "patternContext": "neutral",
      "entryStructure": "no_valid_divert_v0_3_signal",
      "risk": "high",
      "timeframe": "4h",
      "execution": {
        "status": "none",
        "entry": "no action",
        "invalidation": null,
        "exitTrigger": "none",
        "closeRule": "none"
      },
      "setupKey": null,
      "setupIndex": null,
      "setupTimestamp": null,
      "setupState": "idle"
    },
    {
      "symbol": "CRVUSDT",
      "signal": "NO",
      "side": "NONE",
      "quality": "FRAGILE",
      "invalidation": null,
      "scanPrice": 0.23031,
      "sourceVenue": "hyper",
      "notes": [
        "Nu exista inca o structura DiverT valida pe buy sau sell",
        "price_now=0.23031"
      ],
      "patternContext": "neutral",
      "entryStructure": "no_valid_divert_v0_3_signal",
      "risk": "high",
      "timeframe": "4h",
      "execution": {
        "status": "none",
        "entry": "no action",
        "invalidation": null,
        "exitTrigger": "none",
        "closeRule": "none"
      },
      "setupKey": null,
      "setupIndex": null,
      "setupTimestamp": null,
      "setupState": "idle"
    },
    {
      "symbol": "WLDUSDT",
      "signal": "NO",
      "side": "NONE",
      "quality": "FRAGILE",
      "invalidation": null,
      "scanPrice": 0.23232,
      "sourceVenue": "hyper",
      "notes": [
        "Nu exista inca o structura DiverT valida pe buy sau sell",
        "price_now=0.23232"
      ],
      "patternContext": "negative",
      "entryStructure": "no_valid_divert_v0_3_signal",
      "risk": "high",
      "timeframe": "4h",
      "execution": {
        "status": "none",
        "entry": "no action",
        "invalidation": null,
        "exitTrigger": "none",
        "closeRule": "none"
      },
      "setupKey": null,
      "setupIndex": null,
      "setupTimestamp": null,
      "setupState": "idle"
    },
    {
      "symbol": "LTCUSDT",
      "signal": "NO",
      "side": "NONE",
      "quality": "FRAGILE",
      "invalidation": null,
      "scanPrice": 55.305,
      "sourceVenue": "hyper",
      "notes": [
        "Nu exista inca o structura DiverT valida pe buy sau sell",
        "price_now=55.305"
      ],
      "patternContext": "neutral",
      "entryStructure": "no_valid_divert_v0_3_signal",
      "risk": "high",
      "timeframe": "4h",
      "execution": {
        "status": "none",
        "entry": "no action",
        "invalidation": null,
        "exitTrigger": "none",
        "closeRule": "none"
      },
      "setupKey": null,
      "setupIndex": null,
      "setupTimestamp": null,
      "setupState": "idle"
    },
    {
      "symbol": "JUPUSDT",
      "signal": "NO",
      "side": "NONE",
      "quality": "FRAGILE",
      "invalidation": null,
      "scanPrice": 0.17805,
      "sourceVenue": "hyper",
      "notes": [
        "Nu exista inca o structura DiverT valida pe buy sau sell",
        "price_now=0.17805"
      ],
      "patternContext": "neutral",
      "entryStructure": "no_valid_divert_v0_3_signal",
      "risk": "high",
      "timeframe": "4h",
      "execution": {
        "status": "none",
        "entry": "no action",
        "invalidation": null,
        "exitTrigger": "none",
        "closeRule": "none"
      },
      "setupKey": null,
      "setupIndex": null,
      "setupTimestamp": null,
      "setupState": "idle"
    },
    {
      "symbol": "WIFUSDT",
      "signal": "YES",
      "side": "BUY",
      "quality": "GOOD",
      "invalidation": 0.172,
      "scanPrice": 0.18641,
      "sourceVenue": "hyper",
      "notes": [
        "Buy DiverT setup valid",
        "Prima structura valida peste 30 confirmata",
        "Invalidarea defensiva este low-ul setupului",
        "price_now=0.18641"
      ],
      "patternContext": "positive",
      "entryStructure": "buy_divert_v0_3",
      "risk": "medium",
      "timeframe": "4h",
      "execution": {
        "status": "actionable",
        "entry": "direct buy execution on valid setup",
        "invalidation": 0.172,
        "exitTrigger": "take initial bounce / reaction, keep defensive exit active",
        "closeRule": "close on first reaction target or invalidation break"
      },
      "setupKey": "buy:248:271:244:271",
      "setupIndex": 271,
      "setupTimestamp": "2026-04-27T12:00:00+00:00",
      "setupState": "active"
    },
    {
      "symbol": "RUNEUSDT",
      "signal": "NO",
      "side": "NONE",
      "quality": "FRAGILE",
      "invalidation": null,
      "scanPrice": 0.50619,
      "sourceVenue": "hyper",
      "notes": [
        "Nu exista inca o structura DiverT valida pe buy sau sell",
        "price_now=0.50619"
      ],
      "patternContext": "neutral",
      "entryStructure": "no_valid_divert_v0_3_signal",
      "risk": "high",
      "timeframe": "4h",
      "execution": {
        "status": "none",
        "entry": "no action",
        "invalidation": null,
        "exitTrigger": "none",
        "closeRule": "none"
      },
      "setupKey": null,
      "setupIndex": null,
      "setupTimestamp": null,
      "setupState": "idle"
    },
    {
      "symbol": "AEROUSDT",
      "signal": "ERROR",
      "side": "NONE",
      "quality": "UNKNOWN",
      "invalidation": null,
      "scanPrice": 0.46078,
      "sourceVenue": "hyper",
      "notes": [
        "Eroare la generare: HTTP Error 400: Bad Request",
        "price_now=0.46078"
      ],
      "patternContext": "unknown",
      "entryStructure": "error",
      "risk": "unknown",
      "timeframe": "4h",
      "execution": {
        "status": "none",
        "entry": "no action",
        "invalidation": null,
        "exitTrigger": "none",
        "closeRule": "none"
      },
      "setupKey": null,
      "setupIndex": null,
      "setupTimestamp": null,
      "setupState": "idle"
    },
    {
      "symbol": "APTUSDT",
      "signal": "NO",
      "side": "NONE",
      "quality": "FRAGILE",
      "invalidation": null,
      "scanPrice": 0.9895,
      "sourceVenue": "hyper",
      "notes": [
        "Nu exista inca o structura DiverT valida pe buy sau sell",
        "price_now=0.9895"
      ],
      "patternContext": "neutral",
      "entryStructure": "no_valid_divert_v0_3_signal",
      "risk": "high",
      "timeframe": "4h",
      "execution": {
        "status": "none",
        "entry": "no action",
        "invalidation": null,
        "exitTrigger": "none",
        "closeRule": "none"
      },
      "setupKey": null,
      "setupIndex": null,
      "setupTimestamp": null,
      "setupState": "idle"
    },
    {
      "symbol": "DOTUSDT",
      "signal": "NO",
      "side": "NONE",
      "quality": "FRAGILE",
      "invalidation": null,
      "scanPrice": 1.1953,
      "sourceVenue": "hyper",
      "notes": [
        "Nu exista inca o structura DiverT valida pe buy sau sell",
        "price_now=1.1953"
      ],
      "patternContext": "neutral",
      "entryStructure": "no_valid_divert_v0_3_signal",
      "risk": "high",
      "timeframe": "4h",
      "execution": {
        "status": "none",
        "entry": "no action",
        "invalidation": null,
        "exitTrigger": "none",
        "closeRule": "none"
      },
      "setupKey": null,
      "setupIndex": null,
      "setupTimestamp": null,
      "setupState": "idle"
    },
    {
      "symbol": "HBARUSDT",
      "signal": "NO",
      "side": "NONE",
      "quality": "FRAGILE",
      "invalidation": null,
      "scanPrice": 0.08766,
      "sourceVenue": "hyper",
      "notes": [
        "Nu exista inca o structura DiverT valida pe buy sau sell",
        "price_now=0.08766"
      ],
      "patternContext": "neutral",
      "entryStructure": "no_valid_divert_v0_3_signal",
      "risk": "high",
      "timeframe": "4h",
      "execution": {
        "status": "none",
        "entry": "no action",
        "invalidation": null,
        "exitTrigger": "none",
        "closeRule": "none"
      },
      "setupKey": null,
      "setupIndex": null,
      "setupTimestamp": null,
      "setupState": "idle"
    }
  ]
}